{
  "settings": {
    "migrated": 4,
    "iconPacksPath": ".obsidian/icons",
    "fontSize": 16,
    "emojiStyle": "none",
    "iconColor": null,
    "recentlyUsedIcons": [
      "LiHome",
      "LiHeartPulse",
      "LiPanelTop",
      "LiClapperboard",
      "LiInbox"
    ],
    "recentlyUsedIconsSize": 5,
    "rules": [],
    "extraMargin": {
      "top": 0,
      "right": 4,
      "bottom": 0,
      "left": 0
    },
    "iconInTabsEnabled": false,
    "iconInTitleEnabled": false,
    "iconInFrontmatterEnabled": false,
    "iconsBackgroundCheckEnabled": false,
    "iconsInNotesEnabled": true,
    "iconIdentifier": ":"
  },
  "remoteBrain/_template": "LiPanelTop",
  "wooyeon": "LiHand",
  "remoteBrain": "LiInbox",
  "Blog": "LiClapperboard",
  "wooyeon/Love Life": "LiHeartPulse",
  "remoteBrain/Daily-Docs": "LiCalendarCheck2",
  "remoteBrain/Report": "LiFileBarChart"
}